jax_scipy_spatial/distance.py
jax_scipy_spatial/transform.py
jax_scipy_spatial-0.2.5.dist-info/LICENSE
jax_scipy_spatial-0.2.5.dist-info/METADATA
jax_scipy_spatial-0.2.5.dist-info/WHEEL
jax_scipy_spatial-0.2.5.dist-info/top_level.txt
jax_scipy_spatial-0.2.5.dist-info/RECORD
