Metadata-Version: 2.1
Name: jax-scipy-spatial
Version: 0.2.5
Summary: Scipy spatial API for JAX
Author-email: Chris Flesher <chris.flesher@gmail.com>
Project-URL: Homepage, https://github.com/chrisflesher/jax-scipy-spatial
Project-URL: Bug Tracker, https://github.com/chrisflesher/jax-scipy-spatial/issues
Keywords: jax,scipy,spatial,rotation
Classifier: Development Status :: 3 - Alpha
Classifier: Intended Audience :: Developers
Classifier: Intended Audience :: Financial and Insurance Industry
Classifier: Intended Audience :: Information Technology
Classifier: Intended Audience :: Science/Research
Classifier: License :: OSI Approved :: Apache Software License
Classifier: Natural Language :: English
Classifier: Programming Language :: Python :: 3
Classifier: Topic :: Scientific/Engineering :: Artificial Intelligence
Classifier: Topic :: Scientific/Engineering :: Information Analysis
Classifier: Topic :: Scientific/Engineering :: Mathematics
License-File: LICENSE
Requires-Dist: jax
Requires-Dist: jaxlib
Requires-Dist: scipy
Provides-Extra: dev
Requires-Dist: tox ; extra == 'dev'
